HandDec.py
HandDetector_cc-0.0.9.dist-info/LICENSE
HandDetector_cc-0.0.9.dist-info/METADATA
HandDetector_cc-0.0.9.dist-info/WHEEL
HandDetector_cc-0.0.9.dist-info/top_level.txt
HandDetector_cc-0.0.9.dist-info/RECORD
