Metadata-Version: 2.1
Name: HandDetector-cc
Version: 0.0.9
Summary: A simple way to use Mediapipe hand features.
Home-page: https://github.com/Chexa12cc/HandDetector-cc
Author: Chanchal Roy
Author-email: croy7667@gmail.com
Maintainer: Chanchal Roy
Maintainer-email: croy7667@gmail.com
License: MIT
Project-URL: Bug Tracker, https://github.com/Chexa12cc/HandDetector-cc/issues
Keywords: Hand Detection,Opencv,Hand Recognition,Mediapipe
Classifier: Programming Language :: Python :: 3
Classifier: License :: OSI Approved :: MIT License
Classifier: Operating System :: OS Independent
Requires-Python: >=3.6
License-File: LICENSE
Requires-Dist: opencv-contrib-python (==4.6.0.66)
Requires-Dist: mediapipe (==0.8.11)
Requires-Dist: termcolor (==2.0.1)
